altwistendpy/__init__.py
altwistendpy/_version.py
altwistendpy/core.py
altwistendpy/examples/__init__.py
altwistendpy/examples/amp/__init__.py
altwistendpy/examples/amp/cli.py
altwistendpy/examples/amp/client.py
altwistendpy/examples/amp/commands.py
altwistendpy/examples/amp/server.py
altwistendpy-0.0.5.dist-info/METADATA
altwistendpy-0.0.5.dist-info/RECORD
altwistendpy-0.0.5.dist-info/WHEEL
altwistendpy-0.0.5.dist-info/entry_points.txt
altwistendpy-0.0.5.dist-info/top_level.txt
