Metadata-Version: 2.1
Name: altwistendpy
Version: 0.0.5
Summary: Extras for working with Twisted.
Home-page: https://github.com/altendky/altwistendpy
Author: Kyle Altendorf
Author-email: sda@fstab.net
License: UNKNOWN
Platform: UNKNOWN
Classifier: Development Status :: 3 - Alpha
Classifier: Intended Audience :: Developers
Classifier: Programming Language :: Python :: 3
Classifier: Programming Language :: Python :: 3.6
Classifier: Programming Language :: Python :: 3.7
Requires-Dist: attrs
Requires-Dist: click
Requires-Dist: gitignoreio
Requires-Dist: twine
Requires-Dist: twisted
Requires-Dist: wheel
